primer3/__init__.py
primer3/argdefaults.py
primer3/bindings.py
primer3/p3helpers.c
primer3/p3helpers.cpython-310-x86_64-linux-gnu.so
primer3/p3helpers.h
primer3/p3helpers.pxd
primer3/p3helpers.pyx
primer3/thermoanalysis.c
primer3/thermoanalysis.cpython-310-x86_64-linux-gnu.so
primer3/thermoanalysis.pxd
primer3/thermoanalysis.pxi
primer3/thermoanalysis.pyx
primer3/src/libprimer3/ABOUT.txt
primer3/src/libprimer3/LICENSE.txt
primer3/src/libprimer3/Makefile
primer3/src/libprimer3/amplicon3_core
primer3/src/libprimer3/amplicontm.c
primer3/src/libprimer3/amplicontm.h
primer3/src/libprimer3/amplicontm_main.c
primer3/src/libprimer3/dpal.c
primer3/src/libprimer3/dpal.h
primer3/src/libprimer3/format_output.c
primer3/src/libprimer3/format_output.h
primer3/src/libprimer3/gpl-2.0.txt
primer3/src/libprimer3/humrep_and_simple.txt
primer3/src/libprimer3/libprimer3.c
primer3/src/libprimer3/libprimer3.h
primer3/src/libprimer3/libprimer3flex.c
primer3/src/libprimer3/libprimer3flex.h
primer3/src/libprimer3/long_seq_tm_test_main.c
primer3/src/libprimer3/masker.c
primer3/src/libprimer3/masker.h
primer3/src/libprimer3/masker_main.c
primer3/src/libprimer3/ntdpal
primer3/src/libprimer3/ntdpal_main.c
primer3/src/libprimer3/ntthal
primer3/src/libprimer3/oligotm
primer3/src/libprimer3/oligotm.c
primer3/src/libprimer3/oligotm.h
primer3/src/libprimer3/oligotm_main.c
primer3/src/libprimer3/p3_seq_lib.c
primer3/src/libprimer3/p3_seq_lib.h
primer3/src/libprimer3/primer3_boulder_main.c
primer3/src/libprimer3/primer3_core
primer3/src/libprimer3/primer3_masker
primer3/src/libprimer3/print_boulder.c
primer3/src/libprimer3/print_boulder.h
primer3/src/libprimer3/read_boulder.c
primer3/src/libprimer3/read_boulder.h
primer3/src/libprimer3/release_notes.txt
primer3/src/libprimer3/thal.c
primer3/src/libprimer3/thal.h
primer3/src/libprimer3/thal_main.c
primer3/src/libprimer3/thal_parameters.c
primer3/src/libprimer3/thal_parameters.h
primer3_py-2.3.0.dist-info/METADATA
primer3_py-2.3.0.dist-info/WHEEL
primer3_py-2.3.0.dist-info/top_level.txt
primer3_py-2.3.0.dist-info/RECORD
primer3_py-2.3.0.dist-info/licenses/AUTHORS
primer3_py-2.3.0.dist-info/licenses/LICENSE
