Metadata-Version: 2.1
Name: primer3-py
Version: 2.3.0
Summary: Simple primer design and analysis
Author-email: Ben Pruitt <bpruittvt@gmail.com>, Nick Conway <a.grinner@gmail.com>
License: GPLv2
Project-URL: Homepage, https://github.com/libnano/primer3-py
Project-URL: Documentation, http://libnano.github.io/primer3-py
Classifier: Programming Language :: C
Classifier: Programming Language :: Cython
Classifier: Programming Language :: Python
Classifier: Programming Language :: Python :: 3.8
Classifier: Programming Language :: Python :: 3.9
Classifier: Programming Language :: Python :: 3.10
Classifier: Programming Language :: Python :: 3.11
Classifier: Programming Language :: Python :: 3.12
Classifier: Programming Language :: Python :: 3.13
Classifier: Programming Language :: Python :: 3.14
Classifier: Development Status :: 5 - Production/Stable
Classifier: Intended Audience :: Science/Research
Classifier: Topic :: Scientific/Engineering :: Bio-Informatics
Classifier: License :: OSI Approved :: GNU General Public License v2 (GPLv2)
Requires-Python: >=3.8
License-File: LICENSE
License-File: AUTHORS
Provides-Extra: dev
Requires-Dist: pre-commit~=3.5.0; extra == "dev"
Requires-Dist: pytest~=7.4.0; extra == "dev"
Requires-Dist: tomli~=2.0.0; extra == "dev"
Provides-Extra: docs
Requires-Dist: myst-parser; extra == "docs"
Requires-Dist: sphinx; extra == "docs"
Requires-Dist: sphinx-rtd-theme==2.0.0; extra == "docs"
Requires-Dist: sphinx-autodoc-typehints; extra == "docs"
